simulatte/__init__.py
simulatte/builders.py
simulatte/distributions.py
simulatte/environment.py
simulatte/job.py
simulatte/logger.py
simulatte/psp.py
simulatte/router.py
simulatte/runner.py
simulatte/server.py
simulatte/shopfloor.py
simulatte/typing.py
simulatte/experimental/__init__.py
simulatte/experimental/agv.py
simulatte/experimental/builders.py
simulatte/experimental/job.py
simulatte/experimental/materials.py
simulatte/experimental/typing.py
simulatte/experimental/warehouse.py
simulatte/policies/__init__.py
simulatte/policies/lumscor.py
simulatte/policies/slar.py
simulatte/policies/starvation_avoidance.py
simulatte/policies/triggers.py
simulatte-0.2.0.dist-info/METADATA
simulatte-0.2.0.dist-info/WHEEL
simulatte-0.2.0.dist-info/licenses/LICENSE
simulatte-0.2.0.dist-info/RECORD
