Metadata-Version: 2.4
Name: simulatte
Version: 0.2.0
Summary: A discrete-event simulation framework for intralogistics and operations management
Project-URL: Homepage, https://simulatte.dev
Project-URL: Repository, https://github.com/dmezzogori/simulatte
Project-URL: Documentation, https://simulatte.dev
Author-email: Davide Mezzogori <dmezzogori@users.noreply.github.com>
License-Expression: MIT
License-File: LICENSE
Keywords: discrete-event,intralogistics,operations,simpy,simulation
Classifier: Development Status :: 4 - Beta
Classifier: Intended Audience :: Developers
Classifier: Intended Audience :: Science/Research
Classifier: License :: OSI Approved :: MIT License
Classifier: Programming Language :: Python :: 3
Classifier: Programming Language :: Python :: 3.12
Classifier: Programming Language :: Python :: 3.13
Classifier: Programming Language :: Python :: 3.14
Classifier: Topic :: Scientific/Engineering
Classifier: Typing :: Typed
Requires-Python: >=3.12
Requires-Dist: loguru>=0.7.2
Requires-Dist: matplotlib>=3.7.2
Requires-Dist: simpy>=4.0.1
Requires-Dist: tabulate>=0.9.0
Requires-Dist: tqdm>=4.67.1
